README.md
setup.py
FDown.egg-info/PKG-INFO
FDown.egg-info/SOURCES.txt
FDown.egg-info/dependency_links.txt
FDown.egg-info/entry_points.txt
FDown.egg-info/requires.txt
FDown.egg-info/top_level.txt
fdown/__init__.py
fdown/__main__.py
fdown/fdown.py